Workbook

Sheet Start Here
B1: Cohort Logic — Security & Compliance Tracker
B2: SCOPE (2026-07-21): Launching Class Builder + Schedule Builder only (browser-only, no student data stored). CICO + Referral Tracking = Phase 2. Each item is tagged Phase 1 / Phase 2. See compliance/16_Go_To_Market_Scope.md.
B4: Purpose
B5: A single living plan to get Cohort Logic production-ready to sell to schools nationwide — covering FERPA & student-data privacy, security hardening, business/legal/insurance, the questionnaire districts will send you, and the product gaps in between.
B7: How the tabs work
B8: • Dashboard — live rollup: how many items per workstream are done / in progress / not started, and how many P0 (must-have) items remain.
B9: • FERPA & Privacy, Security & Infra, Business & Insurance, Product & Go-Live — the working checklists. Each row has an ID, priority, status, owner, and next action.
B10: • School Vendor Q&A — the recurring questions procurement/IT send, each with a prepared answer, the evidence, and a readiness rating (Ready / Partial / Gap).
B12: How we'll manage it
B13: This is the tracker I (Claude) maintain for you. Tell me things like “mark SE-07 done,” “what are my open P0 items?,” “add a task for X,” or “what do I still owe a district that just sent a questionnaire?” — and I'll update the file and re-share. IDs (FE-/SE-/VQ-/BI-/PR-) are stable handles for that.
B15: Status values (dropdowns)
B16: Checklists: Not started · In progress · Blocked · Done · N/A Vendor Q&A: Ready · Partial · Gap
... B25: Last updated by Claude: 2026-07-21

Sheet Dashboard
A1: Cohort Logic — Production Readiness Dashboard
A2: Live rollup of the workstream tabs. Counts update automatically as Status cells change.
A4: Workstream | B4: P0 items | C4: Not started | D4: In progress | E4: Blocked | F4: Done | G4: % Done
A5: FERPA & Privacy | B5: =COUNTIFS('FERPA & Privacy'!$E$4:$E$200,"P0") | C5: =COUNTIF('FERPA & Privacy'!$F$4:$F$200,"Not started") | D5: =COUNTIF('FERPA & Privacy'!$F$4:$F$200,"In progress") | E5: =COUNTIF('FERPA & Privacy'!$F$4:$F$200,"Blocked") | F5: =COUNTIF('FERPA & Privacy'!$F$4:$F$200,"Done") | G5: =IFERROR(COUNTIF('FERPA & Privacy'!$F$4:$F$200,"Done")/COUNTA('FERPA & Privacy'!$F$4:$F$200),0)
A6: Security & Infra | B6: =COUNTIFS('Security & Infra'!$E$4:$E$200,"P0") | C6: =COUNTIF('Security & Infra'!$F$4:$F$200,"Not started") | D6: =COUNTIF('Security & Infra'!$F$4:$F$200,"In progress") | E6: =COUNTIF('Security & Infra'!$F$4:$F$200,"Blocked") | F6: =COUNTIF('Security & Infra'!$F$4:$F$200,"Done") | G6: =IFERROR(COUNTIF('Security & Infra'!$F$4:$F$200,"Done")/COUNTA('Security & Infra'!$F$4:$F$200),0)
A7: Business & Insurance | B7: =COUNTIFS('Business & Insurance'!$E$4:$E$200,"P0") | C7: =COUNTIF('Business & Insurance'!$F$4:$F$200,"Not started") | D7: =COUNTIF('Business & Insurance'!$F$4:$F$200,"In progress") | E7: =COUNTIF('Business & Insurance'!$F$4:$F$200,"Blocked") | F7: =COUNTIF('Business & Insurance'!$F$4:$F$200,"Done") | G7: =IFERROR(COUNTIF('Business & Insurance'!$F$4:$F$200,"Done")/COUNTA('Business & Insurance'!$F$4:$F$200),0)
A8: Product & Go-Live | B8: =COUNTIFS('Product & Go-Live'!$E$4:$E$200,"P0") | C8: =COUNTIF('Product & Go-Live'!$F$4:$F$200,"Not started") | D8: =COUNTIF('Product & Go-Live'!$F$4:$F$200,"In progress") | E8: =COUNTIF('Product & Go-Live'!$F$4:$F$200,"Blocked") | F8: =COUNTIF('Product & Go-Live'!$F$4:$F$200,"Done") | G8: =IFERROR(COUNTIF('Product & Go-Live'!$F$4:$F$200,"Done")/COUNTA('Product & Go-Live'!$F$4:$F$200),0)
A9: TOTAL | B9: =SUM(B5:B8) | C9: =SUM(C5:C8) | D9: =SUM(D5:D8) | E9: =SUM(E5:E8) | F9: =SUM(F5:F8) | G9: =IFERROR(F9/(C9+D9+E9+F9),0)
A11: School Vendor Questionnaire Readiness
A12: Ready | B12: =COUNTIF('School Vendor Q&A'!$F$4:$F$200,"Ready") | C12: Partial | D12: =COUNTIF('School Vendor Q&A'!$F$4:$F$200,"Partial") | E12: Gap | F12: =COUNTIF('School Vendor Q&A'!$F$4:$F$200,"Gap")
A14: Priority key: | B14: P0 = must-have before selling | P1 = needed early | P2 = important, can follow
A16: Phase 1 launch focus — Class Builder + Schedule Builder (no student data stored)
A17: Phase 1 items | B17: Done | C17: In progress | D17: Not started | E17: % Phase 1 done
A18: =COUNTIF('FERPA & Privacy'!$J$4:$J$200,"Phase 1")+COUNTIF('Security & Infra'!$J$4:$J$200,"Phase 1")+COUNTIF('Business & Insurance'!$J$4:$J$200,"Phase 1")+COUNTIF('Product & Go-Live'!$J$4:$J$200,"Phase 1") | B18: =COUNTIFS('FERPA & Privacy'!$J$4:$J$200,"Phase 1",'FERPA & Privacy'!$F$4:$F$200,"Done")+COUNTIFS('Security & Infra'!$J$4:$J$200,"Phase 1",'Security & Infra'!$F$4:$F$200,"Done")+COUNTIFS('Business & Insurance'!$J$4:$J$200,"Phase 1",'Business & Insurance'!$F$4:$F$200,"Done")+COUNTIFS('Product & Go-Live'!$J$4:$J$200,"Phase 1",'Product & Go-Live'!$F$4:$F$200,"Done") | C18: =COUNTIFS('FERPA & Privacy'!$J$4:$J$200,"Phase 1",'FERPA & Privacy'!$F$4:$F$200,"In progress")+COUNTIFS('Security & Infra'!$J$4:$J$200,"Phase 1",'Security & Infra'!$F$4:$F$200,"In progress")+COUNTIFS('Business & Insurance'!$J$4:$J$200,"Phase 1",'Business & Insurance'!$F$4:$F$200,"In progress")+COUNTIFS('Product & Go-Live'!$J$4:$J$200,"Phase 1",'Product & Go-Live'!$F$4:$F$200,"In progress") | D18: =COUNTIFS('FERPA & Privacy'!$J$4:$J$200,"Phase 1",'FERPA & Privacy'!$F$4:$F$200,"Not started")+COUNTIFS('Security & Infra'!$J$4:$J$200,"Phase 1",'Security & Infra'!$F$4:$F$200,"Not started")+COUNTIFS('Business & Insurance'!$J$4:$J$200,"Phase 1",'Business & Insurance'!$F$4:$F$200,"Not started")+COUNTIFS('Product & Go-Live'!$J$4:$J$200,"Phase 1",'Product & Go-Live'!$F$4:$F$200,"Not started") | E18: =IFERROR(B18/A18,0)
A19: Phase 2 (CICO / Referral Tracking) is deferred until product-market fit — see the Go-To-Market Scope memo (compliance/16).

Sheet FERPA & Privacy
A1: FERPA & Student Data Privacy
A2: Legal basis, contracts, data governance. Attorney review required where noted — this tracker is not legal advice.
A3: ID | B3: Area | C3: Task | D3: Why it matters | E3: Priority | F3: Status | G3: Owner | H3: Depends on | I3: Next action / notes | J3: Phase
A4: FE-01 | B4: Legal basis | C4: Document the FERPA “school official” exception posture (34 CFR §99.31(a)(1)): legitimate educational interest, direct control by the school, use limited to the authorized purpose, no redisclosure. | D4: The legal basis that lets you process student PII without separate parental consent. Every district relies on it. | E4: P0 | F4: In progress | G4: Michael + Attorney | I4: Draft memo at compliance/03_FERPA_School_Official_Posture.md — needs attorney review. | J4: Phase 1
A5: FE-02 | B5: Contracts | C5: Create a signable Data Processing Agreement (DPA) template for schools/districts. | D5: Districts will not sign without one; it is the core of every procurement package. | E5: P0 | F5: In progress | G5: Michael + Attorney | H5: FE-01 | I5: DPA/NDPA readiness at compliance/07_DPA_and_NDPA_Readiness.md — attorney to produce own-paper DPA/MSA. | J5: Phase 1
A6: FE-03 | B6: Standards | C6: Adopt the SDPC National Data Privacy Agreement (NDPA) and join the Student Data Privacy Consortium. | D6: The de-facto national standard; many districts require the NDPA exhibit specifically. | E6: P0 | F6: In progress | G6: Michael | H6: FE-02 | I6: NDPA v2.2 plan in compliance/07_... — join SDPC, prep Exhibit A/B/F, sign Exhibit E (piggyback). | J6: Phase 1
A7: FE-04 | B7: Data map | C7: Produce a data inventory / data-flow map: every PII element collected, its purpose, storage location, access roles, and retention. | D7: Required by NY Ed Law 2-d, IL SOPPA and nearly every vendor questionnaire. | E7: P0 | F7: In progress | G7: Claude | I7: Data map drafted at compliance/01_Data_Inventory_and_Data_Map.md — confirm audit_log PII + Supabase US region. | J7: Phase 1
A8: FE-05 | B8: Sub-processors | C8: Publish the sub-processor list (Supabase / AWS US region, Cloudflare) and obtain each sub-processor DPA. | D8: Districts require the full chain of custody. The Supabase DPA is already an open item in the security audit. | E8: P0 | F8: Not started | G8: Michael | I8: Sign Supabase DPA; get Cloudflare DPA; publish list on the trust page. | J8: Phase 1
A9: FE-06 | B9: Data residency | C9: Confirm and document that all student data (DB + backups) is stored in a US region. | D9: Several states/districts require US-only storage. | E9: P0 | F9: Not started | G9: Michael | I9: Verify Supabase project region in the dashboard; capture attestation. | J9: Phase 1
A10: FE-07 | B10: Retention | C10: Write a data retention & deletion policy; verify per-school deletion on offboarding (admin “Wipe Data” exists) covers all child tables + backups; document the parent/student deletion path via the school. | D10: FERPA + state laws require a defined retention schedule and deletion on request/termination. | E10: P0 | F10: In progress | G10: Michael + Claude | H10: FE-04 | I10: Policy drafted at compliance/02_Data_Retention_and_Deletion_Policy.md — set [DECIDE] windows; verify wipe covers referrals + audit_log. | J10: Phase 1
A11: FE-08 | B11: Privacy policy | C11: Attorney review of privacy.html for FERPA / COPPA / SOPIPA / NY 2-d alignment; add an explicit “no sale, no targeted advertising, no secondary use” statement. | D11: Table-stakes for schools; the current policy has not had legal review. | E11: P0 | F11: In progress | G11: Attorney | I11: Production draft at compliance/08_Privacy_Policy_DRAFT.md — attorney review, then port to privacy.html (fixes Netlify/Schedule/Referrals/demographics gaps). | J11: Phase 1
A12: FE-09 | B12: COPPA | C12: Document the COPPA posture for under-13 students (school acts as agent for parental consent for educational use). | D12: Behavior / CICO data on young students draws COPPA scrutiny. | E12: P1 | F12: Not started | G12: Michael + Attorney | I12: Reflect in privacy policy + DPA. | J12: Phase 2
A13: FE-10 | B13: State laws | C13: Compile a state student-privacy compliance matrix (start: CA SOPIPA, NY Ed Law 2-d, IL SOPPA, CO, VA, TX). | D13: Selling nationwide means multi-state obligations; NY 2-d and IL SOPPA are notably strict. | E13: P1 | F13: In progress | G13: Michael + Claude | I13: State matrix at compliance/06_State_Student_Privacy_Matrix.md — confirm [VERIFY] statute cites/timelines with counsel. | J13: Phase 2
A14: FE-11 | B14: NY Ed Law 2-d | C14: If targeting NY: prepare a Parents Bill of Rights and a Data Security & Privacy Plan aligned to NIST CSF. | D14: NY districts legally cannot sign without these. | E14: P2 | F14: Not started | G14: Michael | H14: FE-10 | I14: Only if pursuing the NY market. | J14: Phase 2
A15: FE-12 | B15: Breach | C15: Document a data-breach notification process with state-law timelines and template notices. | D15: Required by contracts and many state laws (some require notice in ≤ 7 days). | E15: P0 | F15: In progress | G15: Michael + Claude | I15: Breach policy at compliance/05_Data_Breach_Notification_Policy.md — 72h default / 7-day hard ceiling. | J15: Phase 2
A16: FE-13 | B16: Access rights | C16: Document the process for parent/student data access & correction requests, routed through the school. | D16: FERPA access and amendment rights. | E16: P1 | F16: In progress | G16: Michael | H16: FE-07 | I16: Runbook drafted at compliance/14_Data_Request_Runbook.md — set turnaround + privacy@ intake. | J16: Phase 2
A17: FE-14 | B17: Training | C17: Adopt an annual data-privacy & security training / acknowledgement (even solo now; scales with hires). | D17: Questionnaires routinely ask about staff privacy training. | E17: P2 | F17: Not started | G17: Michael | I17: Document the policy now so there is something to point to. | J17: Phase 1

Sheet Security & Infra
A1: Security & Infrastructure Hardening
A2: Technical controls for a production, multi-tenant SaaS. Items marked Done are verified by the daily security agent.
A3: ID | B3: Area | C3: Task | D3: Why it matters | E3: Priority | F3: Status | G3: Owner | H3: Depends on | I3: Next action / notes | J3: Phase
A4: SE-01 | B4: Access control | C4: Multi-tenant data isolation via Postgres RLS (school_id) + role-based access (user / school_admin / super_admin). | D4: Prevents cross-school data leakage; the single most important control. | E4: P0 | F4: Done | G4: — | I4: Verified daily by the security-compliance agent. | J4: Phase 1
A5: SE-02 | B5: Audit | C5: FERPA audit log of data access and changes (audit_log). | D5: Required for FERPA and for incident forensics. | E5: P1 | F5: Done | G5: — | I5: In place. | J5: Phase 1
A6: SE-03 | B6: Transport | C6: TLS + security headers (CSP without unsafe-inline, X-Frame-Options, nosniff, Referrer-Policy, Permissions-Policy) via Cloudflare. | D6: Encryption in transit; a standard questionnaire item. | E6: P0 | F6: Done | G6: — | I6: Verified live by the security agent. | J6: Phase 1
A7: SE-04 | B7: Authentication | C7: Email verification, 15-minute session timeout, admin MFA available. | D7: Baseline account security. | E7: P0 | F7: In progress | G7: Michael | H7: SE-05 | I7: MFA is available but enrollment is not yet mandatory — see SE-05. | J7: Phase 1
A8: SE-05 | B8: Authentication | C8: Enforce mandatory MFA for all admin/staff accounts (block until a factor is verified). | D8: Open audit finding; districts increasingly require enforced MFA. | E8: P1 | F8: Not started | G8: Michael + Claude | I8: Flip admin-mfa.js from soft reminder to hard enforcement. | J8: Phase 1
A9: SE-06 | B9: Monitoring | C9: Automated daily security & compliance audit agent + admin Security dashboard. | D9: Continuous control monitoring; good evidence for buyers. | E9: P1 | F9: Done | G9: — | I9: This agent. | J9: Phase 1
A10: SE-07 | B10: Resilience | C10: Upgrade Supabase to Pro (stops the project pausing on inactivity; unlocks PITR backups). | D10: Required before onboarding any paying school. | E10: P0 | F10: Not started | G10: Michael | I10: Already flagged in CLAUDE.md pending list. | J10: Phase 1
A11: SE-08 | B11: Backups | C11: Enable and document automated backups + Point-in-Time Recovery; run a test restore and record RPO/RTO. | D11: Data durability; a DR and questionnaire requirement. | E11: P0 | F11: Not started | G11: Michael | H11: SE-07 | I11: Document the restore runbook. | J11: Phase 1
A12: SE-09 | B12: Encryption | C12: Confirm and document encryption at rest (Supabase/Postgres + backups); obtain the provider attestation. | D12: Common questionnaire item; pairs with SE-03. | E12: P0 | F12: Not started | G12: Michael | I12: Capture Supabase/AWS attestation language. | J12: Phase 1
A13: SE-10 | B13: Assessment | C13: Commission a third-party penetration test / security assessment; set an annual cadence. | D13: Larger districts ask for pen-test evidence. | E13: P1 | F13: Not started | G13: Michael | I13: Get quotes; schedule the first test. | J13: Phase 2
A14: SE-11 | B14: Vuln mgmt | C14: Establish dependency/vulnerability scanning (npm audit, Dependabot) as an ongoing process. | D14: Ongoing security hygiene. | E14: P2 | F14: Not started | G14: Claude | I14: Add to CI / the pre-deploy gate. | J14: Phase 1
A15: SE-12 | B15: Incident response | C15: Write an Incident Response Plan (roles, severity levels, comms, timelines). | D15: Required by contracts and by FE-12. | E15: P0 | F15: In progress | G15: Michael + Claude | I15: IR plan drafted at compliance/04_Incident_Response_Plan.md — fill [FILL] counsel/insurer/provider contacts. | J15: Phase 1
A16: SE-13 | B16: BC/DR | C16: Write a Business Continuity / Disaster Recovery plan. | D16: Questionnaire item; ties directly to backups. | E16: P1 | F16: In progress | G16: Michael | H16: SE-08 | I16: BC/DR plan drafted at compliance/12_Business_Continuity_and_DR_Plan.md — set RPO/RTO; depends on Supabase Pro (SE-07). | J16: Phase 1
A17: SE-14 | B17: Uptime | C17: Add uptime monitoring + alerting + a public status page. | D17: SLA credibility and a questionnaire item. | E17: P1 | F17: Not started | G17: Michael | I17: e.g. UptimeRobot / BetterStack + a hosted status page. | J17: Phase 1
A18: SE-15 | B18: Passwords | C18: Enable Supabase breached-password protection + a strong password policy. | D18: Cheap, high-value control. | E18: P2 | F18: Not started | G18: Michael | I18: Supabase Auth settings toggle. | J18: Phase 1
A19: SE-16 | B19: Secrets | C19: Document secrets management (service-role key handling + the rotation manifest). | D19: Partly done via security/rotation-manifest.json. | E19: P2 | F19: In progress | G19: Michael | I19: Secrets policy drafted at compliance/13_Secrets_Management.md. | J19: Phase 1
A20: SE-17 | B20: SOC 2 | C20: Decide on a SOC 2 Type I/II roadmap (build now vs defer). | D20: A major enterprise-district sales enabler, but costly and time-consuming. | E20: P2 | F20: Not started | G20: Michael | I20: Decision item; consider Vanta/Drata when revenue supports it. | J20: Phase 2
A21: SE-18 | B21: Edge | C21: Review Cloudflare WAF + rate limiting on auth endpoints. | D21: Brute-force and abuse protection. | E21: P2 | F21: Not started | G21: Michael | I21: Configure WAF rules. | J21: Phase 1

Sheet School Vendor Q&A
A1: School / District Vendor Questionnaire Readiness
A2: The recurring questions procurement and district IT send. Goal: a prepared answer + evidence for every row before the first questionnaire arrives.
A3: ID | B3: Theme | C3: Typical district question | D3: Our current answer | E3: Evidence / where | F3: Status | G3: Action to be answer-ready | H3: Phase
A4: VQ-01 | B4: Company | C4: Legal name, entity type, EIN, years in business, primary contact. | D4: Cohort Logic (confirm exact LLC name + EIN). | E4: Business & Insurance tab | F4: Partial | G4: Confirm entity/EIN (footer 'PBC' vs LLC discrepancy) + document in one place. | H4: Phase 1
A5: VQ-02 | B5: Data collected | C5: What student PII do you collect and why? | D5: Name, grade, homeroom, behavior/CICO records, referral data, limited demographics for equity reporting. No rosters stored for Class Builder. | E5: Data map (FE-04) | F5: Partial | G5: Data map drafted (01_...); finalize + confirm flags. | H5: Phase 1
A6: VQ-03 | B6: Hosting | C6: Where is data hosted? Cloud provider and region? | D6: Supabase (managed Postgres on AWS) + Cloudflare. Confirm US region. | E6: FE-06 | F6: Partial | G6: Confirm + document region. | H6: Phase 1
A7: VQ-04 | B7: Encryption | C7: Is data encrypted in transit and at rest? | D7: In transit: yes (TLS + headers). At rest: pending attestation. | E7: SE-03 done / SE-09 pending | F7: Partial | G7: Obtain at-rest attestation. | H7: Phase 1
A8: VQ-05 | B8: Access control | C8: How is tenant data isolated? RBAC? MFA? | D8: Postgres RLS per school_id; 3-tier roles; admin MFA available. | E8: SE-01 / SE-04 | F8: Ready | G8: Note that mandatory MFA is in progress (SE-05). | H8: Phase 1
A9: VQ-06 | B9: Sub-processors | C9: List your sub-processors and their agreements. | D9: Supabase, Cloudflare. DPAs not yet signed. | E9: FE-05 | F9: Gap | G9: Sub-processor list drafted (01_...); sign Supabase + Cloudflare DPAs to close. | H9: Phase 1
A10: VQ-07 | B10: Retention / deletion | C10: What is your retention schedule and deletion-on-termination process? | D10: Admin Wipe Data exists; formal policy pending. | E10: FE-07 | F10: Partial | G10: Retention/deletion policy drafted (02_...); set windows + verify wipe scope. | H10: Phase 1
A11: VQ-08 | B11: Breach notification | C11: What is your breach notification process and timeline? | D11: Not yet documented. | E11: FE-12 / SE-12 | F11: Partial | G11: Breach policy (05_...) + IR plan (04_...) drafted; fill contacts to reach Ready. | H11: Phase 2
A12: VQ-09 | B12: Compliance | C12: Are you FERPA / COPPA / state-law compliant? Provide statements. | D12: Architecture aligns; statements not attorney-reviewed. | E12: FERPA tab | F12: Partial | G12: FERPA posture (03_...) + state matrix (06_...) drafted; needs counsel-reviewed statements. | H12: Phase 1
A13: VQ-10 | B13: DPA / NDPA | C13: Will you sign our DPA / the SDPC NDPA? | D13: Yes in principle; no template ready yet. | E13: FE-02 / FE-03 | F13: Partial | G13: NDPA readiness brief (07_...) drafted; join SDPC + have signable template to reach Ready. | H13: Phase 1
A14: VQ-11 | B14: Insurance | C14: Do you carry cyber liability and E&O insurance? Limits? COI? | D14: Not yet bound. | E14: Business tab | F14: Partial | G14: Michael obtaining cyber + E&O coverage; keep COI ready once bound (BI-04/05/07). | H14: Phase 1
... A21: VQ-18 | B21: References | C21: Can you provide customer references or pilot results? | D21: None documented yet. | E21: — | F21: Gap | G21: Gather references/testimonials from pilots. | H21: Phase 1

Sheet Business & Insurance
A1: Business, Legal & Insurance
A2: Entity, contracts and coverage. Insurance rows are informational only — consult a licensed broker; this is not insurance or financial advice.
A3: ID | B3: Area | C3: Task | D3: Why it matters | E3: Priority | F3: Status | G3: Owner | H3: Depends on | I3: Next action / notes | J3: Phase
A4: BI-01 | B4: Entity | C4: Confirm LLC formation, registered agent, and a current operating agreement. | D4: Contracts require a valid, in-good-standing legal entity. | E4: P0 | F4: Not started | G4: Michael | I4: Confirm exact legal entity — security.html footer says 'PBC', other materials imply LLC; make consistent. | J4: Phase 1
A5: BI-02 | B5: Tax | C5: Have EIN + a signed W-9 ready to hand to districts. | D5: Districts require a W-9 to set you up as a vendor/payee. | E5: P0 | F5: Not started | G5: Michael | H5: BI-01 | I5: Keep a signed W-9 on file. | J5: Phase 1
A6: BI-03 | B6: Banking | C6: Business bank account + clean accounting separation. | D6: Basic operations + audit readiness. | E6: P1 | F6: In progress | G6: Michael | I6: Confirm (bookkeeping already underway). | J6: Phase 1
A7: BI-04 | B7: Insurance | C7: Obtain Cyber Liability / data-breach insurance (districts often require $1-2M). | D7: Frequently a contractual requirement and protects the business after an incident. | E7: P0 | F7: In progress | G7: Michael + Broker | I7: Michael obtaining cyber liability coverage (broker). | J7: Phase 1
A8: BI-05 | B8: Insurance | C8: Obtain Technology E&O / Professional Liability. | D8: Covers claims that your software caused a customer loss. | E8: P0 | F8: In progress | G8: Michael + Broker | I8: Michael obtaining technology E&O coverage (broker). | J8: Phase 1
A9: BI-06 | B9: Insurance | C9: General Liability (commonly a BOP bundle). | D9: A common contract requirement. | E9: P1 | F9: In progress | G9: Michael + Broker | I9: Michael obtaining general liability / BOP (broker). | J9: Phase 1
A10: BI-07 | B10: Insurance | C10: Keep a Certificate of Insurance (COI) ready for procurement. | D10: Districts request a COI before signing. | E10: P1 | F10: Not started | G10: Michael | H10: BI-04 | I10: Store a current COI to attach to questionnaires. | J10: Phase 1
A11: BI-08 | B11: Legal | C11: Attorney-reviewed Terms of Service (currently terms-beta.html). | D11: “Beta” terms are not adequate for paid district contracts. | E11: P0 | F11: In progress | G11: Attorney | I11: Production ToS draft at compliance/09_Terms_of_Service_DRAFT.md — replaces beta agreement; attorney review then port to terms.html. | J11: Phase 1
A12: BI-09 | B12: Legal | C12: Master Services / Subscription Agreement for schools. | D12: The commercial contract for paying customers. | E12: P0 | F12: In progress | G12: Attorney | I12: MSA skeleton at compliance/10_Master_Services_Agreement_SKELETON.md — attorney to draft; contract doc, not a web page. | J12: Phase 1
A13: BI-10 | B13: Legal | C13: DPA template as a contract exhibit (mirrors FE-02). | D13: The data-handling terms of the MSA. | E13: P0 | F13: Not started | G13: Attorney | H13: FE-02 | I13: Keep the legal and product copies in sync. | J13: Phase 1
A14: BI-11 | B14: Legal | C14: Acceptable Use Policy. | D14: Governs how customers may use the product. | E14: P2 | F14: In progress | G14: Michael | I14: AUP draft at compliance/11_Acceptable_Use_Policy_DRAFT.md. | J14: Phase 1
A15: BI-12 | B15: IP | C15: Consider a trademark for “Cohort Logic”. | D15: Brand protection as you scale nationally. | E15: P2 | F15: Not started | G15: Michael | I15: Optional; search availability first. | J15: Phase 2
A16: BI-13 | B16: Procurement | C16: Prepare to register in district/state vendor systems as required. | D16: Some districts require formal vendor registration. | E16: P2 | F16: Not started | G16: Michael | I16: Handle as encountered. | J16: Phase 2
A17: BI-14 | B17: Counsel | C17: Identify ed-tech/privacy legal counsel + breach counsel. | D17: Speed matters for both contract review and incident response. | E17: P1 | F17: Not started | G17: Michael | I17: Have someone on call before the first deal. | J17: Phase 1

Sheet Product & Go-Live
A1: Product & Go-Live Readiness
A2: The commercial and product gaps between “works” and “sellable nationwide.”
A3: ID | B3: Area | C3: Task | D3: Why it matters | E3: Priority | F3: Status | G3: Owner | H3: Depends on | I3: Next action / notes | J3: Phase
A4: PR-01 | B4: Billing | C4: Integrate a payment processor (Stripe) for subscriptions; wire to the subscriptions table. | D4: You cannot sell without billing, and there is no processor yet. | E4: P0 | F4: Not started | G4: Michael + Claude | I4: Design plans + checkout + webhooks. | J4: Phase 1
A5: PR-02 | B5: Onboarding | C5: Build/document the school onboarding flow (provision school, first admin, roster import). | D5: A smooth setup drives conversion and reduces support. | E5: P1 | F5: In progress | G5: Michael + Claude | I5: Admin tooling exists; formalize the flow. | J5: Phase 1
A6: PR-03 | B6: Support | C6: Define support channels + SLA + response-time targets. | D6: A questionnaire item and a trust signal. | E6: P1 | F6: Not started | G6: Michael | I6: e.g. email + help desk; publish response targets. | J6: Phase 1
A7: PR-04 | B7: Docs | C7: Help center / user documentation. | D7: Reduces support load; a procurement plus. | E7: P2 | F7: Not started | G7: Michael | I7: Start with top workflows per product. | J7: Phase 1
A8: PR-05 | B8: Accessibility | C8: Commission a WCAG 2.1 AA audit and produce a VPAT. | D8: Increasingly required in K-12 procurement (Section 508 / ADA). | E8: P1 | F8: Not started | G8: Michael | I8: Feeds VQ-13. | J8: Phase 1
A9: PR-06 | B9: SSO / rostering | C9: Roadmap Google / Clever / ClassLink SSO + roster sync. | D9: A major K-12 adoption and IT-approval factor. | E9: P1 | F9: Not started | G9: Michael + Claude | I9: Feeds VQ-14; sequence after billing. | J9: Phase 2
A10: PR-07 | B10: Reliability | C10: Publish an uptime SLA commitment + status page. | D10: Ties to SE-14; buyers ask for it. | E10: P2 | F10: Not started | G10: Michael | H10: SE-14 | J10: Phase 1
A11: PR-08 | B11: Infra cleanup | C11: Delete the legacy Netlify site; confirm a single production path. | D11: Reduces attack surface and deployment confusion. | E11: P2 | F11: Not started | G11: Michael | I11: Already in CLAUDE.md pending. | J11: Phase 1
A12: PR-09 | B12: Pricing | C12: Finalize pricing and plan tiers (pricing.html exists). | D12: Needed for billing and sales conversations. | E12: P1 | F12: In progress | G12: Michael | I12: Confirm tiers before wiring Stripe. | J12: Phase 1
A13: PR-10 | B13: Trust page | C13: Expand security.html into a public Trust/Security page (controls, sub-processors, compliance posture). | D13: A sales asset that pre-answers most questionnaires. | E13: P1 | F13: In progress | G13: Michael + Claude | H13: FE-05 | I13: Trust page content drafted at compliance/15_Trust_Page_Content.md — product-aware reframe; port to security.html in website batch. | J13: Phase 1
